drf_feedback/__init__.py
drf_feedback/admin.py
drf_feedback/apps.py
drf_feedback/models.py
drf_feedback/serializers.py
drf_feedback/tests.py
drf_feedback/urls.py
drf_feedback/views.py
drf_feedback/migrations/0001_initial.py
drf_feedback/migrations/__init__.py
drf_feedback-0.0.3.dist-info/METADATA
drf_feedback-0.0.3.dist-info/RECORD
drf_feedback-0.0.3.dist-info/WHEEL
drf_feedback-0.0.3.dist-info/top_level.txt
