Metadata-Version: 2.1
Name: drf-feedback
Version: 0.0.3
Summary: Feedback APP for Django REST Framework with API Views.
Home-page: https://github.com/civilmachines/drf-feedback
Author: Civil Machines Technologies Private Limited
Author-email: pypidev@civilmachines.com
License: GPLv3
Platform: UNKNOWN
Classifier: Development Status :: 5 - Production/Stable
Classifier: Environment :: Web Environment
Classifier: Framework :: Django
Classifier: Framework :: Django :: 1.10
Classifier: Framework :: Django :: 1.11
Classifier: Framework :: Django :: 2.0
Classifier: Intended Audience :: Developers
Classifier: License :: OSI Approved :: GNU General Public License v3 (GPLv3)
Classifier: Operating System :: OS Independent
Classifier: Programming Language :: Python
Classifier: Programming Language :: Python :: 3
Classifier: Programming Language :: Python :: 3.4
Classifier: Programming Language :: Python :: 3.5
Classifier: Programming Language :: Python :: 3.6
Classifier: Topic :: Internet :: WWW/HTTP
Requires-Python: >=2.7, !=3.0.*, !=3.1.*, !=3.2.*, !=3.3.*
Requires-Dist: Django (<=2.0.5)
Requires-Dist: PyJWT (<=1.6.4)
Requires-Dist: djangorestframework-jwt (<=1.11.0)
Requires-Dist: djangorestframework (<=3.8.2)
Requires-Dist: drfaddons (<=0.0.2)
Requires-Dist: pytz (<=2018.4)
